amaranth_yosys/__init__.py
amaranth_yosys/__main__.py
amaranth_yosys/yosys.wasm
amaranth_yosys/share/include/backends/cxxrtl/runtime/cxxrtl/cxxrtl.h
amaranth_yosys/share/include/backends/cxxrtl/runtime/cxxrtl/cxxrtl_replay.h
amaranth_yosys/share/include/backends/cxxrtl/runtime/cxxrtl/cxxrtl_time.h
amaranth_yosys/share/include/backends/cxxrtl/runtime/cxxrtl/cxxrtl_vcd.h
amaranth_yosys/share/include/backends/cxxrtl/runtime/cxxrtl/capi/cxxrtl_capi.cc
amaranth_yosys/share/include/backends/cxxrtl/runtime/cxxrtl/capi/cxxrtl_capi.h
amaranth_yosys/share/include/backends/cxxrtl/runtime/cxxrtl/capi/cxxrtl_capi_vcd.cc
amaranth_yosys/share/include/backends/cxxrtl/runtime/cxxrtl/capi/cxxrtl_capi_vcd.h
amaranth_yosys-0.50.0.0.post120.dist-info/licenses/LICENSE.txt
amaranth_yosys-0.50.0.0.post120.dist-info/METADATA
amaranth_yosys-0.50.0.0.post120.dist-info/WHEEL
amaranth_yosys-0.50.0.0.post120.dist-info/top_level.txt
amaranth_yosys-0.50.0.0.post120.dist-info/RECORD
