Metadata-Version: 2.4
Name: amaranth-yosys
Version: 0.50.0.0.post120
Summary: Specialized WebAssembly build of Yosys used by Amaranth HDL
Author-email: whitequark <whitequark@whitequark.org>
License-Expression: ISC
Project-URL: Source Code, https://github.com/amaranth-lang/amaranth-yosys
Project-URL: Bug Tracker, https://github.com/amaranth-lang/amaranth-yosys/issues
Requires-Python: ~=3.8
License-File: LICENSE.txt
Requires-Dist: importlib_resources>=1.4; python_version < "3.9"
Requires-Dist: wasmtime<42,>=1
Dynamic: license-file
